odoo/addons/ddmrp_coverage_days/README.rst
odoo/addons/ddmrp_coverage_days/__init__.py
odoo/addons/ddmrp_coverage_days/__manifest__.py
odoo/addons/ddmrp_coverage_days/i18n/ddmrp_coverage_days.pot
odoo/addons/ddmrp_coverage_days/models/__init__.py
odoo/addons/ddmrp_coverage_days/models/stock_buffer.py
odoo/addons/ddmrp_coverage_days/readme/CONTRIBUTORS.rst
odoo/addons/ddmrp_coverage_days/readme/DESCRIPTION.rst
odoo/addons/ddmrp_coverage_days/readme/HISTORY.rst
odoo/addons/ddmrp_coverage_days/static/description/icon.png
odoo/addons/ddmrp_coverage_days/static/description/index.html
odoo/addons/ddmrp_coverage_days/tests/__init__.py
odoo/addons/ddmrp_coverage_days/tests/test_ddmrp_coverage_days.py
odoo/addons/ddmrp_coverage_days/views/stock_buffer_views.xml
odoo13_addon_ddmrp_coverage_days-13.0.1.2.0.dist-info/METADATA
odoo13_addon_ddmrp_coverage_days-13.0.1.2.0.dist-info/WHEEL
odoo13_addon_ddmrp_coverage_days-13.0.1.2.0.dist-info/top_level.txt
odoo13_addon_ddmrp_coverage_days-13.0.1.2.0.dist-info/RECORD
